CHANGES.txt
PapyDVD.ini
README.txt
setup.cfg
setup.py
PapyDVD.egg-info/PKG-INFO
PapyDVD.egg-info/SOURCES.txt
PapyDVD.egg-info/dependency_links.txt
PapyDVD.egg-info/entry_points.txt
PapyDVD.egg-info/not-zip-safe
PapyDVD.egg-info/requires.txt
PapyDVD.egg-info/top_level.txt
papydvd/__init__.py
papydvd/configure.zcml
papydvd/models.py
papydvd/run.py
papydvd/utils.py
papydvd/views.py
papydvd/locale/PapyDVD.pot
papydvd/locale/it/LC_MESSAGES/PapyDVD.po
papydvd/templates/directors.pt
papydvd/templates/genres.pt
papydvd/templates/main.pt
papydvd/templates/main_template.pt
papydvd/templates/static/images/ajax-loader.gif
papydvd/templates/static/images/arrow_left.png
papydvd/templates/static/images/arrow_right.png
papydvd/templates/static/images/delete.png
papydvd/templates/static/images/edit.png
papydvd/templates/static/images/favicon.gif
papydvd/templates/static/images/logo.png
papydvd/templates/static/images/required.gif
papydvd/templates/static/images/ui-bg_diagonals-small_0_aaaaaa_40x40.png
papydvd/templates/static/images/ui-bg_diagonals-thick_15_444444_40x40.png
papydvd/templates/static/images/ui-bg_diagonals-thick_95_ffdc2e_40x40.png
papydvd/templates/static/images/ui-bg_glass_55_fbf5d0_1x400.png
papydvd/templates/static/images/ui-bg_highlight-hard_30_285c00_1x100.png
papydvd/templates/static/images/ui-bg_highlight-soft_33_3a8104_1x100.png
papydvd/templates/static/images/ui-bg_highlight-soft_50_4eb305_1x100.png
papydvd/templates/static/images/ui-bg_highlight-soft_60_4ca20b_1x100.png
papydvd/templates/static/images/ui-bg_inset-soft_10_285c00_1x100.png
papydvd/templates/static/images/ui-icons_4eb305_256x240.png
papydvd/templates/static/images/ui-icons_72b42d_256x240.png
papydvd/templates/static/images/ui-icons_cd0a0a_256x240.png
papydvd/templates/static/images/ui-icons_ffffff_256x240.png
papydvd/templates/static/javascript/jquery-1.4.4.min.js
papydvd/templates/static/javascript/jquery-ui.min.js
papydvd/templates/static/javascript/jquery.jgrowl_minimized.js
papydvd/templates/static/javascript/papydvd.js
papydvd/templates/static/styles/decogrids-12.css
papydvd/templates/static/styles/default.css
papydvd/templates/static/styles/jquery-ui.css
