Metadata-Version: 1.0
Name: PapyDVD
Version: 0.0.3
Summary: Simple Web application for manage a personal database of DVD movies
Home-page: http://sourceforge.net/projects/papydvd/
Author: keul
Author-email: luca@keul.it
License: UNKNOWN
Keywords: web wsgi bfg dvd database
Platform: UNKNOWN
Classifier: Programming Language :: Python
Classifier: Framework :: BFG
Classifier: Development Status :: 2 - Pre-Alpha
Classifier: Natural Language :: Italian
Classifier: Topic :: Internet :: WWW/HTTP
Classifier: Topic :: Internet :: WWW/HTTP :: WSGI :: Application
